2021.1 - Sistemas Digitais/trabalho_final/registrador.v
module registrador (
    
    input sel,
    input [15:0] entrada,
    input clk,
    output reg [15:0] saida
);
    
    always @(posedge clk ) begin
        if (sel == 1) begin
            saida <= entrada;
        end
    end

endmodule

2021.1 - Sistemas Digitais/trabalho_final/mux4x1.v
module mux4x1 (

    input [1:0] sel,
    input [15:0] dado1,
    input [15:0] dado2,
    input [15:0] dado3,
    input [15:0] dado4,

    output [15:0] saida
);

    assign saida = sel == 0 ?dado1 : sel == 1 ?dado2 : sel == 2 ?dado3 : dado4; 

    
endmodule

2021.1 - Sistemas Digitais/trabalho_final/ula.v
module ula (
    input h,
    input [15:0] m2,
    input [15:0] m1,
    output [15:0] out
);

    assign out = h? m1 * m2 : m1 + m2;

endmodule

2021.1 - Sistemas Digitais/trabalho_final/blocoOperativo.v
`include "mux4x1.v"
`include "ula.v"
`include "registrador.v"


module blocoOperativo (

    /* valores: */
    input [7:0] X,
    input [15:0] A,
    input [15:0] B,
    input [15:0] C,

    /* controladores dos mux: */
    input [1:0] M0,
    input [1:0] M1,
    input [1:0] M2,

    /* carregadores dos regs: */
    input LX,
    input LS,
    input LH,

    /* controlador ULA: */
    input h,

    /* clock */
    input clk,

    /* resultado: */
    output [15:0] resultado
);

/* ligações:  */

    wire [15:0] saida_LX;
    wire [15:0] saida_LS;
    wire [15:0] saida_LH;
    wire [15:0] saida_MuxM0;
    wire [15:0] saida_MuxM1;
    wire [15:0] saida_MuxM2;
    wire [15:0] saida_ULA;
    wire [15:0] saida_X16bits;
    wire [15:0] op1_MuxM0;

    assign saida_X16bits = X;
    assign op1_MuxM0 = 0;




    //instanciamentos:

    ula ula0(h, saida_MuxM2, saida_MuxM1, saida_ULA);
 
    mux4x1 m0(M0, op1_MuxM0, A, B, C, saida_MuxM0);
    mux4x1 m1(M1, saida_MuxM0, saida_X16bits, saida_LS, saida_LH, saida_MuxM1);
    mux4x1 m2(M2, saida_X16bits, saida_MuxM0, saida_LS, saida_LH, saida_MuxM2);

    registrador reg_LX(LX, saida_X16bits, clk, saida_LX);
    registrador reg_LS(LS, saida_ULA, clk, saida_LS);
    registrador reg_LH(LH, saida_ULA, clk, saida_LH);


    assign resultado = saida_LS;

endmodule

2021.1 - Sistemas Digitais/trabalho_final/blocoDeControle.v
module blocoDeControle (
    input reset,
    input clk,
    input inicio,
    output [1:0] M0,
    output [1:0] M1,
    output [1:0] M2,
    output regLX,
    output regLS,
    output regLH,
    output H,
    output pronto,
    output comecou
);

reg[3:0] state;

    always @(posedge clk or reset) begin

        if (reset) // =1
            state <= 0; //reiniciaremos

        else begin
            if (state == 0 && ~inicio)
                state <= state;
            else begin
                if(state == 8)
                    state <= 0;
                else begin
                state <= state + 1; //incremento
                end
            end
        end
    end

//lógica implementação dos estados

//assign variavel1 = variavel2 == X1? X2 : X3 | x1,x2,x3 são numeros
//variavel1 q vai receber o valor
//se o valor da variavel2 for igual a X1, a variavel1 recebe X2, se não recebe X3 */
//modelo:
//assign variavel = state == 0? x : state == 1? x : state == 2? x : state == 3? x : state == 4? x : state == 5? x : state == 6? x : state == 7? x : 0; */

assign M0 = state == 3? 1 : state == 4? 2 : state == 5? 0 : state == 6? 3 : 0;

assign M1 = state == 1? 1 : state == 2? 1 : state == 3? 3 : state == 4? 0 : state == 5? 3 : state == 6? 0 : 0;

assign M2 = state == 1? 0 : state == 2? 0 : state == 3? 1 : state == 4? 0 : state == 5? 2 : state == 6? 2 : 0;

assign regLX = state == 1? 1 : 0;

assign regLS = state == 3? 1 : state == 4? 0 : state == 5? 1 : state == 6? 1 : 0;

assign regLH = state == 2? 1 : state == 3? 0 : state == 4? 1 : 0;

assign H = state == 1? 1 : state == 2? 1 : state == 3? 1 : state == 4? 1 : state == 5? 0 : state == 6? 0 : 0;

assign comecou = state == 0? 1 : state == 1? 0 : state == 2? 0 : state == 3? 0 : state == 4? 0 : state == 5? 0 : state == 6? 0 : state == 7? 0 : 0;

assign pronto = state == 0? 0 : state == 1? 0 : state == 2? 0 : state == 3? 0 : state == 4? 0 : state == 5? 0 : state == 6? 0 : state == 7? 1 : 0;



endmodule

2021.1 - Sistemas Digitais/trabalho_final/operacao.v
`include "blocoDeControle.v"
`include "blocoOperativo.v"

module operacao (
    input reset,
    input clk,
    input inicio,
    input [7:0] X,
    input [15:0] A,
    input [15:0] B,
    input [15:0] C,
    output [15:0] resultado,
    output pronto,
    output comecou
    
);

    wire [1:0] M0;
    wire [1:0] M1;
    wire [1:0] M2;
    wire LX;
    wire LS;
    wire LH;
    wire H;

    blocoDeControle BC(reset, clk, inicio, M0, M1, M2, LX, LS, LH, H, pronto, comecou);
    blocoOperativo BO(X, A, B, C, M0, M1, M2, LX, LS, LH, H, clk, resultado);

    
endmodule

2021.1 - Sistemas Digitais/trabalho_final/testbench.v
`include "operacao.v"

module testbench;


    reg reset = 0;
    reg clk = 0;
    reg inicio = 0;
    reg [7:0] X = 2;
    reg [15:0] A = 1;
    reg [15:0] B = 2;
    reg [15:0] C = 5;
    wire [15:0] resultado;
    wire pronto;
    wire comecou;

    //instanciamento do modulo operação
    operacao resolve(reset, clk, inicio, X, A, B, C, resultado, pronto, comecou);

    always #1 clk <= ~clk;

    initial begin
        $dumpvars;
        reset <= 1;

        #1;

        reset <= 0;
        inicio <= 1;

    #16
        $finish;
    end

    
endmodule

2021.1 - Sistemas Digitais/trabalho_final/dump.vcd
$date
	Tue Sep 21 19:19:59 2021
$end
$version
	Icarus Verilog
$end
$timescale
	1s
$end
$scope module testbench $end
$var wire 16 ! resultado [15:0] $end
$var wire 1 " pronto $end
$var wire 1 # comecou $end
$var reg 16 $ A [15:0] $end
$var reg 16 % B [15:0] $end
$var reg 16 & C [15:0] $end
$var reg 8 ' X [7:0] $end
$var reg 1 ( clk $end
$var reg 1 ) inicio $end
$var reg 1 * reset $end
$scope module resolve $end
$var wire 16 + A [15:0] $end
$var wire 16 , B [15:0] $end
$var wire 16 - C [15:0] $end
$var wire 8 . X [7:0] $end
$var wire 1 ( clk $end
$var wire 1 ) inicio $end
$var wire 1 * reset $end
$var wire 16 / resultado [15:0] $end
$var wire 1 " pronto $end
$var wire 1 # comecou $end
$var wire 2 0 M2 [1:0] $end
$var wire 2 1 M1 [1:0] $end
$var wire 2 2 M0 [1:0] $end
$var wire 1 3 LX $end
$var wire 1 4 LS $end
$var wire 1 5 LH $end
$var wire 1 6 H $end
$scope module BC $end
$var wire 1 ( clk $end
$var wire 1 ) inicio $end
$var wire 1 * reset $end
$var wire 1 3 regLX $end
$var wire 1 4 regLS $end
$var wire 1 5 regLH $end
$var wire 1 " pronto $end
$var wire 1 # comecou $end
$var wire 2 7 M2 [1:0] $end
$var wire 2 8 M1 [1:0] $end
$var wire 2 9 M0 [1:0] $end
$var wire 1 6 H $end
$var reg 4 : state [3:0] $end
$upscope $end
$scope module BO $end
$var wire 16 ; A [15:0] $end
$var wire 16 < B [15:0] $end
$var wire 16 = C [15:0] $end
$var wire 1 5 LH $end
$var wire 1 4 LS $end
$var wire 1 3 LX $end
$var wire 2 > M0 [1:0] $end
$var wire 2 ? M1 [1:0] $end
$var wire 2 @ M2 [1:0] $end
$var wire 8 A X [7:0] $end
$var wire 1 ( clk $end
$var wire 1 6 h $end
$var wire 16 B op1_MuxM0 [15:0] $end
$var wire 16 C resultado [15:0] $end
$var wire 16 D saida_X16bits [15:0] $end
$var wire 16 E saida_ULA [15:0] $end
$var wire 16 F saida_MuxM2 [15:0] $end
$var wire 16 G saida_MuxM1 [15:0] $end
$var wire 16 H saida_MuxM0 [15:0] $end
$var wire 16 I saida_LX [15:0] $end
$var wire 16 J saida_LS [15:0] $end
$var wire 16 K saida_LH [15:0] $end
$scope module m0 $end
$var wire 16 L dado1 [15:0] $end
$var wire 16 M dado2 [15:0] $end
$var wire 16 N dado3 [15:0] $end
$var wire 16 O dado4 [15:0] $end
$var wire 2 P sel [1:0] $end
$var wire 16 Q saida [15:0] $end
$upscope $end
$scope module m1 $end
$var wire 16 R dado1 [15:0] $end
$var wire 16 S dado2 [15:0] $end
$var wire 2 T sel [1:0] $end
$var wire 16 U saida [15:0] $end
$var wire 16 V dado4 [15:0] $end
$var wire 16 W dado3 [15:0] $end
$upscope $end
$scope module m2 $end
$var wire 16 X dado1 [15:0] $end
$var wire 16 Y dado2 [15:0] $end
$var wire 2 Z sel [1:0] $end
$var wire 16 [ saida [15:0] $end
$var wire 16 \ dado4 [15:0] $end
$var wire 16 ] dado3 [15:0] $end
$upscope $end
$scope module reg_LH $end
$var wire 1 ( clk $end
$var wire 1 5 sel $end
$var wire 16 ^ entrada [15:0] $end
$var reg 16 _ saida [15:0] $end
$upscope $end
$scope module reg_LS $end
$var wire 1 ( clk $end
$var wire 1 4 sel $end
$var wire 16 ` entrada [15:0] $end
$var reg 16 a saida [15:0] $end
$upscope $end
$scope module reg_LX $end
$var wire 1 ( clk $end
$var wire 16 b entrada [15:0] $end
$var wire 1 3 sel $end
$var reg 16 c saida [15:0] $end
$upscope $end
$scope module ula0 $end
$var wire 1 6 h $end
$var wire 16 d m1 [15:0] $end
$var wire 16 e m2 [15:0] $end
$var wire 16 f out [15:0] $end
$upscope $end
$upscope $end
$upscope $end
$upscope $end
$enddefinitions $end
#0
$dumpvars
b10 f
b10 e
b0 d
bx c
b10 b
bx a
b10 `
bx _
b10 ^
bx ]
bx \
b10 [
b0 Z
b0 Y
b10 X
bx W
bx V
b0 U
b0 T
b10 S
b0 R
b0 Q
b0 P
b101 O
b10 N
b1 M
b0 L
bx K
bx J
bx I
b0 H
b0 G
b10 F
b10 E
b10 D
bx C
b0 B
b10 A
b0 @
b0 ?
b0 >
b101 =
b10 <
b1 ;
b0 :
b0 9
b0 8
b0 7
06
05
04
03
b0 2
b0 1
b0 0
bx /
b10 .
b101 -
b10 ,
b1 +
1*
0)
0(
b10 '
b101 &
b10 %
b1 $
1#
0"
bx !
$end
#1
b10 G
b10 U
b10 d
b100 E
b100 ^
b100 `
b100 f
b1 1
b1 8
b1 ?
b1 T
13
16
0#
b1 :
1)
0*
1(
#2
0(
#3
03
15
b10 :
b10 I
b10 c
1(
#4
0(
#5
b100 G
b100 U
b100 d
b100 E
b100 ^
b100 `
b100 f
b1 F
b1 [
b1 e
b1 H
b1 Q
b1 R
b1 Y
b11 1
b11 8
b11 ?
b11 T
b1 0
b1 7
b1 @
b1 Z
b1 2
b1 9
b1 >
b1 P
14
05
b11 :
b100 K
b100 V
b100 \
b100 _
1(
#6
0(
#7
b10 G
b10 U
b10 d
b10 F
b10 [
b10 e
b10 H
b10 Q
b10 R
b10 Y
b0 1
b0 8
b0 ?
b0 T
b0 0
b0 7
b0 @
b0 Z
15
b10 2
b10 9
b10 >
b10 P
04
b100 :
b100 !
b100 /
b100 C
b100 J
b100 W
b100 ]
b100 a
1(
#8
0(
#9
b100 F
b100 [
b100 e
b1000 E
b1000 ^
b1000 `
b1000 f
b100 G
b100 U
b100 d
b11 1
b11 8
b11 ?
b11 T
b10 0
b10 7
b10 @
b10 Z
06
b0 H
b0 Q
b0 R
b0 Y
05
b0 2
b0 9
b0 >
b0 P
14
b101 :
1(
#10
0(
#11
b101 G
b101 U
b101 d
b0 1
b0 8
b0 ?
b0 T
b101 H
b101 Q
b101 R
b101 Y
b11 2
b11 9
b11 >
b11 P
b1101 E
b1101 ^
b1101 `
b1101 f
b1000 F
b1000 [
b1000 e
b110 :
b1000 !
b1000 /
b1000 C
b1000 J
b1000 W
b1000 ]
b1000 a
1(
#12
0(
#13
1"
b0 G
b0 U
b0 d
b0 0
b0 7
b0 @
b0 Z
b0 H
b0 Q
b0 R
b0 Y
b0 2
b0 9
b0 >
b0 P
04
b10 E
b10 ^
b10 `
b10 f
b10 F
b10 [
b10 e
b111 :
b1101 !
b1101 /
b1101 C
b1101 J
b1101 W
b1101 ]
b1101 a
1(
#14
0(
#15
0"
b1000 :
1(
#16
0(
#17
1#
b0 :
1(
